[
  {
    "title": "تعداد بازدید وب‌سایت‌ها",
    "value": 1099000,
    "growth": 10,
    "chartData": [
      {
        "day": "شنبه",
        "visits": 153624
      },
      {
        "day": "یک‌شنبه",
        "visits": 166474
      },
      {
        "day": "دوشنبه",
        "visits": 148754
      },
      {
        "day": "سه‌شنبه",
        "visits": 156864
      },
      {
        "day": "چهارشنبه",
        "visits": 164224
      },
      {
        "day": "پنج‌شنبه",
        "visits": 177554
      },
      {
        "day": "جمعه",
        "visits": 145784
      }
    ]
  },
  {
    "title": "تعداد کاربران جدید",
    "value": 3893,
    "growth": 5,
    "chartData": [
      {
        "day": "شنبه",
        "visits": 4572
      },
      {
        "day": "یک‌شنبه",
        "visits": 4579
      },
      {
        "day": "دوشنبه",
        "visits": 4574
      },
      {
        "day": "سه‌شنبه",
        "visits": 4583
      },
      {
        "day": "چهارشنبه",
        "visits": 4576
      },
      {
        "day": "پنج‌شنبه",
        "visits": 4578
      },
      {
        "day": "جمعه",
        "visits": 4589
      }
    ]
  },
  {
    "title": "وب‌سایت‌های زیرمجموعه",
    "value": 3855,
    "growth": 3,
    "chartData": [
      {
        "day": "شنبه",
        "visits": 4582
      },
      {
        "day": "یک‌شنبه",
        "visits": 4579
      },
      {
        "day": "دوشنبه",
        "visits": 4607
      },
      {
        "day": "سه‌شنبه",
        "visits": 4581
      },
      {
        "day": "چهارشنبه",
        "visits": 4575
      },
      {
        "day": "پنج‌شنبه",
        "visits": 4608
      },
      {
        "day": "جمعه",
        "visits": 4581
      }
    ]
  },
  {
    "title": "سرورهای فعال",
    "value": 3893,
    "growth": 2,
    "chartData": [
      {
        "day": "شنبه",
        "visits": 4574
      },
      {
        "day": "یک‌شنبه",
        "visits": 4575
      },
      {
        "day": "دوشنبه",
        "visits": 4581
      },
      {
        "day": "سه‌شنبه",
        "visits": 4583
      },
      {
        "day": "چهارشنبه",
        "visits": 4579
      },
      {
        "day": "پنج‌شنبه",
        "visits": 4576
      },
      {
        "day": "جمعه",
        "visits": 4663
      }
    ]
  },
  {
    "title": "تحلیل‌های امروز",
    "value": 3927,
    "growth": 4,
    "chartData": [
      {
        "day": "شنبه",
        "visits": 4659
      },
      {
        "day": "یک‌شنبه",
        "visits": 4570
      },
      {
        "day": "دوشنبه",
        "visits": 4661
      },
      {
        "day": "سه‌شنبه",
        "visits": 4571
      },
      {
        "day": "چهارشنبه",
        "visits": 4572
      },
      {
        "day": "پنج‌شنبه",
        "visits": 4761
      },
      {
        "day": "جمعه",
        "visits": 4761
      }
    ]
  },
  {
    "title": "قطع همکاری‌های هفته اخیر",
    "value": 3901,
    "growth": -9,
    "chartData": [
      {
        "day": "شنبه",
        "visits": 4611
      },
      {
        "day": "یک‌شنبه",
        "visits": 4604
      },
      {
        "day": "دوشنبه",
        "visits": 4613
      },
      {
        "day": "سه‌شنبه",
        "visits": 4605
      },
      {
        "day": "چهارشنبه",
        "visits": 4612
      },
      {
        "day": "پنج‌شنبه",
        "visits": 4611
      },
      {
        "day": "جمعه",
        "visits": 4613
      }
    ]
  }
]