[
  {
    "title": "تعداد بازدید وب‌سایت‌ها",
    "value": 1139730,
    "growth": 10,
    "chartData": [
      {
        "day": "شنبه",
        "visits": 202500
      },
      {
        "day": "یک‌شنبه",
        "visits": 215350
      },
      {
        "day": "دوشنبه",
        "visits": 197630
      },
      {
        "day": "سه‌شنبه",
        "visits": 205740
      },
      {
        "day": "چهارشنبه",
        "visits": 213100
      },
      {
        "day": "پنج‌شنبه",
        "visits": 226430
      },
      {
        "day": "جمعه",
        "visits": 194660
      }
    ]
  },
  {
    "title": "تعداد کاربران جدید",
    "value": 40523,
    "growth": 5,
    "chartData": [
      {
        "day": "شنبه",
        "visits": 48648
      },
      {
        "day": "یک‌شنبه",
        "visits": 48655
      },
      {
        "day": "دوشنبه",
        "visits": 48650
      },
      {
        "day": "سه‌شنبه",
        "visits": 48659
      },
      {
        "day": "چهارشنبه",
        "visits": 48652
      },
      {
        "day": "پنج‌شنبه",
        "visits": 48654
      },
      {
        "day": "جمعه",
        "visits": 48665
      }
    ]
  },
  {
    "title": "وب‌سایت‌های زیرمجموعه",
    "value": 44585,
    "growth": 3,
    "chartData": [
      {
        "day": "شنبه",
        "visits": 48658
      },
      {
        "day": "یک‌شنبه",
        "visits": 48655
      },
      {
        "day": "دوشنبه",
        "visits": 48583
      },
      {
        "day": "سه‌شنبه",
        "visits": 48657
      },
      {
        "day": "چهارشنبه",
        "visits": 48651
      },
      {
        "day": "پنج‌شنبه",
        "visits": 48584
      },
      {
        "day": "جمعه",
        "visits": 48657
      }
    ]
  },
  {
    "title": "سرورهای فعال",
    "value": 40523,
    "growth": 2,
    "chartData": [
      {
        "day": "شنبه",
        "visits": 48650
      },
      {
        "day": "یک‌شنبه",
        "visits": 48651
      },
      {
        "day": "دوشنبه",
        "visits": 48657
      },
      {
        "day": "سه‌شنبه",
        "visits": 48659
      },
      {
        "day": "چهارشنبه",
        "visits": 48655
      },
      {
        "day": "پنج‌شنبه",
        "visits": 48652
      },
      {
        "day": "جمعه",
        "visits": 48639
      }
    ]
  },
  {
    "title": "تحلیل‌های امروز",
    "value": 40557,
    "growth": 4,
    "chartData": [
      {
        "day": "شنبه",
        "visits": 48635
      },
      {
        "day": "یک‌شنبه",
        "visits": 48646
      },
      {
        "day": "دوشنبه",
        "visits": 48637
      },
      {
        "day": "سه‌شنبه",
        "visits": 48647
      },
      {
        "day": "چهارشنبه",
        "visits": 48648
      },
      {
        "day": "پنج‌شنبه",
        "visits": 48637
      },
      {
        "day": "جمعه",
        "visits": 48637
      }
    ]
  },
  {
    "title": "قطع همکاری‌های هفته اخیر",
    "value": 40531,
    "growth": -9,
    "chartData": [
      {
        "day": "شنبه",
        "visits": 48587
      },
      {
        "day": "یک‌شنبه",
        "visits": 48580
      },
      {
        "day": "دوشنبه",
        "visits": 48589
      },
      {
        "day": "سه‌شنبه",
        "visits": 48581
      },
      {
        "day": "چهارشنبه",
        "visits": 48488
      },
      {
        "day": "پنج‌شنبه",
        "visits": 48487
      },
      {
        "day": "جمعه",
        "visits": 48489
      }
    ]
  }
]