[
  {
    "title": "تعداد بازدید وب‌سایت‌ها",
    "value": 1102100,
    "growth": 10,
    "chartData": [
      {
        "day": "شنبه",
        "visits": 157344
      },
      {
        "day": "یک‌شنبه",
        "visits": 170194
      },
      {
        "day": "دوشنبه",
        "visits": 152474
      },
      {
        "day": "سه‌شنبه",
        "visits": 160584
      },
      {
        "day": "چهارشنبه",
        "visits": 167944
      },
      {
        "day": "پنج‌شنبه",
        "visits": 181274
      },
      {
        "day": "جمعه",
        "visits": 149504
      }
    ]
  },
  {
    "title": "تعداد کاربران جدید",
    "value": 2893,
    "growth": 5,
    "chartData": [
      {
        "day": "شنبه",
        "visits": 3492
      },
      {
        "day": "یک‌شنبه",
        "visits": 3499
      },
      {
        "day": "دوشنبه",
        "visits": 3494
      },
      {
        "day": "سه‌شنبه",
        "visits": 3503
      },
      {
        "day": "چهارشنبه",
        "visits": 3496
      },
      {
        "day": "پنج‌شنبه",
        "visits": 3498
      },
      {
        "day": "جمعه",
        "visits": 3509
      }
    ]
  },
  {
    "title": "وب‌سایت‌های زیرمجموعه",
    "value": 6955,
    "growth": 3,
    "chartData": [
      {
        "day": "شنبه",
        "visits": 3502
      },
      {
        "day": "یک‌شنبه",
        "visits": 3499
      },
      {
        "day": "دوشنبه",
        "visits": 3427
      },
      {
        "day": "سه‌شنبه",
        "visits": 3501
      },
      {
        "day": "چهارشنبه",
        "visits": 3495
      },
      {
        "day": "پنج‌شنبه",
        "visits": 3428
      },
      {
        "day": "جمعه",
        "visits": 3501
      }
    ]
  },
  {
    "title": "سرورهای فعال",
    "value": 2893,
    "growth": 2,
    "chartData": [
      {
        "day": "شنبه",
        "visits": 3494
      },
      {
        "day": "یک‌شنبه",
        "visits": 3495
      },
      {
        "day": "دوشنبه",
        "visits": 3501
      },
      {
        "day": "سه‌شنبه",
        "visits": 3503
      },
      {
        "day": "چهارشنبه",
        "visits": 3499
      },
      {
        "day": "پنج‌شنبه",
        "visits": 3496
      },
      {
        "day": "جمعه",
        "visits": 3483
      }
    ]
  },
  {
    "title": "تحلیل‌های امروز",
    "value": 2927,
    "growth": 4,
    "chartData": [
      {
        "day": "شنبه",
        "visits": 3479
      },
      {
        "day": "یک‌شنبه",
        "visits": 3490
      },
      {
        "day": "دوشنبه",
        "visits": 3481
      },
      {
        "day": "سه‌شنبه",
        "visits": 3491
      },
      {
        "day": "چهارشنبه",
        "visits": 3492
      },
      {
        "day": "پنج‌شنبه",
        "visits": 3481
      },
      {
        "day": "جمعه",
        "visits": 3481
      }
    ]
  },
  {
    "title": "قطع همکاری‌های هفته اخیر",
    "value": 2901,
    "growth": -9,
    "chartData": [
      {
        "day": "شنبه",
        "visits": 3431
      },
      {
        "day": "یک‌شنبه",
        "visits": 3424
      },
      {
        "day": "دوشنبه",
        "visits": 3433
      },
      {
        "day": "سه‌شنبه",
        "visits": 3425
      },
      {
        "day": "چهارشنبه",
        "visits": 3332
      },
      {
        "day": "پنج‌شنبه",
        "visits": 3331
      },
      {
        "day": "جمعه",
        "visits": 3333
      }
    ]
  }
]