[
  {
    "title": "تعداد بازدید وب‌سایت‌ها",
    "value": 1103840,
    "growth": 10,
    "chartData": [
      {
        "day": "شنبه",
        "visits": 159432
      },
      {
        "day": "یک‌شنبه",
        "visits": 172282
      },
      {
        "day": "دوشنبه",
        "visits": 154562
      },
      {
        "day": "سه‌شنبه",
        "visits": 162672
      },
      {
        "day": "چهارشنبه",
        "visits": 170032
      },
      {
        "day": "پنج‌شنبه",
        "visits": 183362
      },
      {
        "day": "جمعه",
        "visits": 151592
      }
    ]
  },
  {
    "title": "تعداد کاربران جدید",
    "value": 4633,
    "growth": 5,
    "chartData": [
      {
        "day": "شنبه",
        "visits": 5580
      },
      {
        "day": "یک‌شنبه",
        "visits": 5587
      },
      {
        "day": "دوشنبه",
        "visits": 5582
      },
      {
        "day": "سه‌شنبه",
        "visits": 5591
      },
      {
        "day": "چهارشنبه",
        "visits": 5584
      },
      {
        "day": "پنج‌شنبه",
        "visits": 5586
      },
      {
        "day": "جمعه",
        "visits": 5597
      }
    ]
  },
  {
    "title": "وب‌سایت‌های زیرمجموعه",
    "value": 8695,
    "growth": 3,
    "chartData": [
      {
        "day": "شنبه",
        "visits": 5590
      },
      {
        "day": "یک‌شنبه",
        "visits": 5587
      },
      {
        "day": "دوشنبه",
        "visits": 5515
      },
      {
        "day": "سه‌شنبه",
        "visits": 5589
      },
      {
        "day": "چهارشنبه",
        "visits": 5583
      },
      {
        "day": "پنج‌شنبه",
        "visits": 5516
      },
      {
        "day": "جمعه",
        "visits": 5589
      }
    ]
  },
  {
    "title": "سرورهای فعال",
    "value": 4633,
    "growth": 2,
    "chartData": [
      {
        "day": "شنبه",
        "visits": 5582
      },
      {
        "day": "یک‌شنبه",
        "visits": 5583
      },
      {
        "day": "دوشنبه",
        "visits": 5589
      },
      {
        "day": "سه‌شنبه",
        "visits": 5591
      },
      {
        "day": "چهارشنبه",
        "visits": 5587
      },
      {
        "day": "پنج‌شنبه",
        "visits": 5584
      },
      {
        "day": "جمعه",
        "visits": 5571
      }
    ]
  },
  {
    "title": "تحلیل‌های امروز",
    "value": 4667,
    "growth": 4,
    "chartData": [
      {
        "day": "شنبه",
        "visits": 5567
      },
      {
        "day": "یک‌شنبه",
        "visits": 5578
      },
      {
        "day": "دوشنبه",
        "visits": 5569
      },
      {
        "day": "سه‌شنبه",
        "visits": 5579
      },
      {
        "day": "چهارشنبه",
        "visits": 5580
      },
      {
        "day": "پنج‌شنبه",
        "visits": 5569
      },
      {
        "day": "جمعه",
        "visits": 5569
      }
    ]
  },
  {
    "title": "قطع همکاری‌های هفته اخیر",
    "value": 4641,
    "growth": -9,
    "chartData": [
      {
        "day": "شنبه",
        "visits": 5519
      },
      {
        "day": "یک‌شنبه",
        "visits": 5512
      },
      {
        "day": "دوشنبه",
        "visits": 5521
      },
      {
        "day": "سه‌شنبه",
        "visits": 5513
      },
      {
        "day": "چهارشنبه",
        "visits": 5420
      },
      {
        "day": "پنج‌شنبه",
        "visits": 5419
      },
      {
        "day": "جمعه",
        "visits": 5421
      }
    ]
  }
]