[
  {
    "title": "تعداد بازدید وب‌سایت‌ها",
    "value": 1149920,
    "growth": 10,
    "chartData": [
      {
        "day": "شنبه",
        "visits": 214728
      },
      {
        "day": "یک‌شنبه",
        "visits": 227578
      },
      {
        "day": "دوشنبه",
        "visits": 209858
      },
      {
        "day": "سه‌شنبه",
        "visits": 217968
      },
      {
        "day": "چهارشنبه",
        "visits": 225328
      },
      {
        "day": "پنج‌شنبه",
        "visits": 238658
      },
      {
        "day": "جمعه",
        "visits": 206888
      }
    ]
  },
  {
    "title": "تعداد کاربران جدید",
    "value": 50713,
    "growth": 5,
    "chartData": [
      {
        "day": "شنبه",
        "visits": 60876
      },
      {
        "day": "یک‌شنبه",
        "visits": 60883
      },
      {
        "day": "دوشنبه",
        "visits": 60878
      },
      {
        "day": "سه‌شنبه",
        "visits": 60887
      },
      {
        "day": "چهارشنبه",
        "visits": 60880
      },
      {
        "day": "پنج‌شنبه",
        "visits": 60882
      },
      {
        "day": "جمعه",
        "visits": 60893
      }
    ]
  },
  {
    "title": "وب‌سایت‌های زیرمجموعه",
    "value": 54775,
    "growth": 3,
    "chartData": [
      {
        "day": "شنبه",
        "visits": 60886
      },
      {
        "day": "یک‌شنبه",
        "visits": 60883
      },
      {
        "day": "دوشنبه",
        "visits": 60811
      },
      {
        "day": "سه‌شنبه",
        "visits": 60885
      },
      {
        "day": "چهارشنبه",
        "visits": 60879
      },
      {
        "day": "پنج‌شنبه",
        "visits": 60812
      },
      {
        "day": "جمعه",
        "visits": 60885
      }
    ]
  },
  {
    "title": "سرورهای فعال",
    "value": 50713,
    "growth": 2,
    "chartData": [
      {
        "day": "شنبه",
        "visits": 60878
      },
      {
        "day": "یک‌شنبه",
        "visits": 60879
      },
      {
        "day": "دوشنبه",
        "visits": 60885
      },
      {
        "day": "سه‌شنبه",
        "visits": 60887
      },
      {
        "day": "چهارشنبه",
        "visits": 60883
      },
      {
        "day": "پنج‌شنبه",
        "visits": 60880
      },
      {
        "day": "جمعه",
        "visits": 60867
      }
    ]
  },
  {
    "title": "تحلیل‌های امروز",
    "value": 50747,
    "growth": 4,
    "chartData": [
      {
        "day": "شنبه",
        "visits": 60863
      },
      {
        "day": "یک‌شنبه",
        "visits": 60874
      },
      {
        "day": "دوشنبه",
        "visits": 60865
      },
      {
        "day": "سه‌شنبه",
        "visits": 60875
      },
      {
        "day": "چهارشنبه",
        "visits": 60876
      },
      {
        "day": "پنج‌شنبه",
        "visits": 60865
      },
      {
        "day": "جمعه",
        "visits": 60865
      }
    ]
  },
  {
    "title": "قطع همکاری‌های هفته اخیر",
    "value": 50721,
    "growth": -9,
    "chartData": [
      {
        "day": "شنبه",
        "visits": 60815
      },
      {
        "day": "یک‌شنبه",
        "visits": 60808
      },
      {
        "day": "دوشنبه",
        "visits": 60817
      },
      {
        "day": "سه‌شنبه",
        "visits": 60809
      },
      {
        "day": "چهارشنبه",
        "visits": 60716
      },
      {
        "day": "پنج‌شنبه",
        "visits": 60715
      },
      {
        "day": "جمعه",
        "visits": 60717
      }
    ]
  }
]