[
  {
    "title": "تعداد بازدید وب‌سایت‌ها",
    "value": 1118870,
    "growth": 10,
    "chartData": [
      {
        "day": "شنبه",
        "visits": 177468
      },
      {
        "day": "یک‌شنبه",
        "visits": 190318
      },
      {
        "day": "دوشنبه",
        "visits": 172598
      },
      {
        "day": "سه‌شنبه",
        "visits": 180708
      },
      {
        "day": "چهارشنبه",
        "visits": 188068
      },
      {
        "day": "پنج‌شنبه",
        "visits": 201398
      },
      {
        "day": "جمعه",
        "visits": 169628
      }
    ]
  },
  {
    "title": "تعداد کاربران جدید",
    "value": 19663,
    "growth": 5,
    "chartData": [
      {
        "day": "شنبه",
        "visits": 23616
      },
      {
        "day": "یک‌شنبه",
        "visits": 23623
      },
      {
        "day": "دوشنبه",
        "visits": 23618
      },
      {
        "day": "سه‌شنبه",
        "visits": 23627
      },
      {
        "day": "چهارشنبه",
        "visits": 23620
      },
      {
        "day": "پنج‌شنبه",
        "visits": 23622
      },
      {
        "day": "جمعه",
        "visits": 23633
      }
    ]
  },
  {
    "title": "وب‌سایت‌های زیرمجموعه",
    "value": 23725,
    "growth": 3,
    "chartData": [
      {
        "day": "شنبه",
        "visits": 23626
      },
      {
        "day": "یک‌شنبه",
        "visits": 23623
      },
      {
        "day": "دوشنبه",
        "visits": 23551
      },
      {
        "day": "سه‌شنبه",
        "visits": 23625
      },
      {
        "day": "چهارشنبه",
        "visits": 23619
      },
      {
        "day": "پنج‌شنبه",
        "visits": 23552
      },
      {
        "day": "جمعه",
        "visits": 23625
      }
    ]
  },
  {
    "title": "سرورهای فعال",
    "value": 19663,
    "growth": 2,
    "chartData": [
      {
        "day": "شنبه",
        "visits": 23618
      },
      {
        "day": "یک‌شنبه",
        "visits": 23619
      },
      {
        "day": "دوشنبه",
        "visits": 23625
      },
      {
        "day": "سه‌شنبه",
        "visits": 23627
      },
      {
        "day": "چهارشنبه",
        "visits": 23623
      },
      {
        "day": "پنج‌شنبه",
        "visits": 23620
      },
      {
        "day": "جمعه",
        "visits": 23607
      }
    ]
  },
  {
    "title": "تحلیل‌های امروز",
    "value": 19697,
    "growth": 4,
    "chartData": [
      {
        "day": "شنبه",
        "visits": 23603
      },
      {
        "day": "یک‌شنبه",
        "visits": 23614
      },
      {
        "day": "دوشنبه",
        "visits": 23605
      },
      {
        "day": "سه‌شنبه",
        "visits": 23615
      },
      {
        "day": "چهارشنبه",
        "visits": 23616
      },
      {
        "day": "پنج‌شنبه",
        "visits": 23605
      },
      {
        "day": "جمعه",
        "visits": 23605
      }
    ]
  },
  {
    "title": "قطع همکاری‌های هفته اخیر",
    "value": 19671,
    "growth": -9,
    "chartData": [
      {
        "day": "شنبه",
        "visits": 23555
      },
      {
        "day": "یک‌شنبه",
        "visits": 23548
      },
      {
        "day": "دوشنبه",
        "visits": 23557
      },
      {
        "day": "سه‌شنبه",
        "visits": 23549
      },
      {
        "day": "چهارشنبه",
        "visits": 23456
      },
      {
        "day": "پنج‌شنبه",
        "visits": 23455
      },
      {
        "day": "جمعه",
        "visits": 23457
      }
    ]
  }
]