[
  {
    "title": "تعداد بازدید وب‌سایت‌ها",
    "value": 1131500,
    "growth": 10,
    "chartData": [
      {
        "day": "شنبه",
        "visits": 192624
      },
      {
        "day": "یک‌شنبه",
        "visits": 205474
      },
      {
        "day": "دوشنبه",
        "visits": 187754
      },
      {
        "day": "سه‌شنبه",
        "visits": 195864
      },
      {
        "day": "چهارشنبه",
        "visits": 203224
      },
      {
        "day": "پنج‌شنبه",
        "visits": 216554
      },
      {
        "day": "جمعه",
        "visits": 184784
      }
    ]
  },
  {
    "title": "تعداد کاربران جدید",
    "value": 32293,
    "growth": 5,
    "chartData": [
      {
        "day": "شنبه",
        "visits": 38772
      },
      {
        "day": "یک‌شنبه",
        "visits": 38779
      },
      {
        "day": "دوشنبه",
        "visits": 38774
      },
      {
        "day": "سه‌شنبه",
        "visits": 38783
      },
      {
        "day": "چهارشنبه",
        "visits": 38776
      },
      {
        "day": "پنج‌شنبه",
        "visits": 38778
      },
      {
        "day": "جمعه",
        "visits": 38789
      }
    ]
  },
  {
    "title": "وب‌سایت‌های زیرمجموعه",
    "value": 36355,
    "growth": 3,
    "chartData": [
      {
        "day": "شنبه",
        "visits": 38782
      },
      {
        "day": "یک‌شنبه",
        "visits": 38779
      },
      {
        "day": "دوشنبه",
        "visits": 38707
      },
      {
        "day": "سه‌شنبه",
        "visits": 38781
      },
      {
        "day": "چهارشنبه",
        "visits": 38775
      },
      {
        "day": "پنج‌شنبه",
        "visits": 38708
      },
      {
        "day": "جمعه",
        "visits": 38781
      }
    ]
  },
  {
    "title": "سرورهای فعال",
    "value": 32293,
    "growth": 2,
    "chartData": [
      {
        "day": "شنبه",
        "visits": 38774
      },
      {
        "day": "یک‌شنبه",
        "visits": 38775
      },
      {
        "day": "دوشنبه",
        "visits": 38781
      },
      {
        "day": "سه‌شنبه",
        "visits": 38783
      },
      {
        "day": "چهارشنبه",
        "visits": 38779
      },
      {
        "day": "پنج‌شنبه",
        "visits": 38776
      },
      {
        "day": "جمعه",
        "visits": 38763
      }
    ]
  },
  {
    "title": "تحلیل‌های امروز",
    "value": 32327,
    "growth": 4,
    "chartData": [
      {
        "day": "شنبه",
        "visits": 38759
      },
      {
        "day": "یک‌شنبه",
        "visits": 38770
      },
      {
        "day": "دوشنبه",
        "visits": 38761
      },
      {
        "day": "سه‌شنبه",
        "visits": 38771
      },
      {
        "day": "چهارشنبه",
        "visits": 38772
      },
      {
        "day": "پنج‌شنبه",
        "visits": 38761
      },
      {
        "day": "جمعه",
        "visits": 38761
      }
    ]
  },
  {
    "title": "قطع همکاری‌های هفته اخیر",
    "value": 32301,
    "growth": -9,
    "chartData": [
      {
        "day": "شنبه",
        "visits": 38711
      },
      {
        "day": "یک‌شنبه",
        "visits": 38704
      },
      {
        "day": "دوشنبه",
        "visits": 38713
      },
      {
        "day": "سه‌شنبه",
        "visits": 38705
      },
      {
        "day": "چهارشنبه",
        "visits": 38612
      },
      {
        "day": "پنج‌شنبه",
        "visits": 38611
      },
      {
        "day": "جمعه",
        "visits": 38613
      }
    ]
  }
]