[
  {
    "title": "تعداد بازدید وب‌سایت‌ها",
    "value": 1144790,
    "growth": 10,
    "chartData": [
      {
        "day": "شنبه",
        "visits": 208572
      },
      {
        "day": "یک‌شنبه",
        "visits": 221422
      },
      {
        "day": "دوشنبه",
        "visits": 203702
      },
      {
        "day": "سه‌شنبه",
        "visits": 211812
      },
      {
        "day": "چهارشنبه",
        "visits": 219172
      },
      {
        "day": "پنج‌شنبه",
        "visits": 232502
      },
      {
        "day": "جمعه",
        "visits": 200732
      }
    ]
  },
  {
    "title": "تعداد کاربران جدید",
    "value": 45583,
    "growth": 5,
    "chartData": [
      {
        "day": "شنبه",
        "visits": 54720
      },
      {
        "day": "یک‌شنبه",
        "visits": 54727
      },
      {
        "day": "دوشنبه",
        "visits": 54722
      },
      {
        "day": "سه‌شنبه",
        "visits": 54731
      },
      {
        "day": "چهارشنبه",
        "visits": 54724
      },
      {
        "day": "پنج‌شنبه",
        "visits": 54726
      },
      {
        "day": "جمعه",
        "visits": 54737
      }
    ]
  },
  {
    "title": "وب‌سایت‌های زیرمجموعه",
    "value": 49645,
    "growth": 3,
    "chartData": [
      {
        "day": "شنبه",
        "visits": 54730
      },
      {
        "day": "یک‌شنبه",
        "visits": 54727
      },
      {
        "day": "دوشنبه",
        "visits": 54655
      },
      {
        "day": "سه‌شنبه",
        "visits": 54729
      },
      {
        "day": "چهارشنبه",
        "visits": 54723
      },
      {
        "day": "پنج‌شنبه",
        "visits": 54656
      },
      {
        "day": "جمعه",
        "visits": 54729
      }
    ]
  },
  {
    "title": "سرورهای فعال",
    "value": 45583,
    "growth": 2,
    "chartData": [
      {
        "day": "شنبه",
        "visits": 54722
      },
      {
        "day": "یک‌شنبه",
        "visits": 54723
      },
      {
        "day": "دوشنبه",
        "visits": 54729
      },
      {
        "day": "سه‌شنبه",
        "visits": 54731
      },
      {
        "day": "چهارشنبه",
        "visits": 54727
      },
      {
        "day": "پنج‌شنبه",
        "visits": 54724
      },
      {
        "day": "جمعه",
        "visits": 54711
      }
    ]
  },
  {
    "title": "تحلیل‌های امروز",
    "value": 45617,
    "growth": 4,
    "chartData": [
      {
        "day": "شنبه",
        "visits": 54707
      },
      {
        "day": "یک‌شنبه",
        "visits": 54718
      },
      {
        "day": "دوشنبه",
        "visits": 54709
      },
      {
        "day": "سه‌شنبه",
        "visits": 54719
      },
      {
        "day": "چهارشنبه",
        "visits": 54720
      },
      {
        "day": "پنج‌شنبه",
        "visits": 54709
      },
      {
        "day": "جمعه",
        "visits": 54709
      }
    ]
  },
  {
    "title": "قطع همکاری‌های هفته اخیر",
    "value": 45591,
    "growth": -9,
    "chartData": [
      {
        "day": "شنبه",
        "visits": 54659
      },
      {
        "day": "یک‌شنبه",
        "visits": 54652
      },
      {
        "day": "دوشنبه",
        "visits": 54661
      },
      {
        "day": "سه‌شنبه",
        "visits": 54653
      },
      {
        "day": "چهارشنبه",
        "visits": 54560
      },
      {
        "day": "پنج‌شنبه",
        "visits": 54559
      },
      {
        "day": "جمعه",
        "visits": 54561
      }
    ]
  }
]