[
  {
    "title": "تعداد بازدید وب‌سایت‌ها",
    "value": 1098400,
    "growth": 10,
    "chartData": [
      {
        "day": "شنبه",
        "visits": 152904
      },
      {
        "day": "یک‌شنبه",
        "visits": 165754
      },
      {
        "day": "دوشنبه",
        "visits": 148034
      },
      {
        "day": "سه‌شنبه",
        "visits": 156144
      },
      {
        "day": "چهارشنبه",
        "visits": 163504
      },
      {
        "day": "پنج‌شنبه",
        "visits": 176834
      },
      {
        "day": "جمعه",
        "visits": 145064
      }
    ]
  },
  {
    "title": "تعداد کاربران جدید",
    "value": 3293,
    "growth": 5,
    "chartData": [
      {
        "day": "شنبه",
        "visits": 3852
      },
      {
        "day": "یک‌شنبه",
        "visits": 3859
      },
      {
        "day": "دوشنبه",
        "visits": 3854
      },
      {
        "day": "سه‌شنبه",
        "visits": 3863
      },
      {
        "day": "چهارشنبه",
        "visits": 3856
      },
      {
        "day": "پنج‌شنبه",
        "visits": 3858
      },
      {
        "day": "جمعه",
        "visits": 3869
      }
    ]
  },
  {
    "title": "وب‌سایت‌های زیرمجموعه",
    "value": 3255,
    "growth": 3,
    "chartData": [
      {
        "day": "شنبه",
        "visits": 3862
      },
      {
        "day": "یک‌شنبه",
        "visits": 3859
      },
      {
        "day": "دوشنبه",
        "visits": 3887
      },
      {
        "day": "سه‌شنبه",
        "visits": 3861
      },
      {
        "day": "چهارشنبه",
        "visits": 3855
      },
      {
        "day": "پنج‌شنبه",
        "visits": 3888
      },
      {
        "day": "جمعه",
        "visits": 3861
      }
    ]
  },
  {
    "title": "سرورهای فعال",
    "value": 3293,
    "growth": 2,
    "chartData": [
      {
        "day": "شنبه",
        "visits": 3854
      },
      {
        "day": "یک‌شنبه",
        "visits": 3855
      },
      {
        "day": "دوشنبه",
        "visits": 3861
      },
      {
        "day": "سه‌شنبه",
        "visits": 3863
      },
      {
        "day": "چهارشنبه",
        "visits": 3859
      },
      {
        "day": "پنج‌شنبه",
        "visits": 3856
      },
      {
        "day": "جمعه",
        "visits": 3943
      }
    ]
  },
  {
    "title": "تحلیل‌های امروز",
    "value": 3327,
    "growth": 4,
    "chartData": [
      {
        "day": "شنبه",
        "visits": 3939
      },
      {
        "day": "یک‌شنبه",
        "visits": 3850
      },
      {
        "day": "دوشنبه",
        "visits": 3941
      },
      {
        "day": "سه‌شنبه",
        "visits": 3851
      },
      {
        "day": "چهارشنبه",
        "visits": 3852
      },
      {
        "day": "پنج‌شنبه",
        "visits": 4041
      },
      {
        "day": "جمعه",
        "visits": 4041
      }
    ]
  },
  {
    "title": "قطع همکاری‌های هفته اخیر",
    "value": 3301,
    "growth": -9,
    "chartData": [
      {
        "day": "شنبه",
        "visits": 3891
      },
      {
        "day": "یک‌شنبه",
        "visits": 3884
      },
      {
        "day": "دوشنبه",
        "visits": 3893
      },
      {
        "day": "سه‌شنبه",
        "visits": 3885
      },
      {
        "day": "چهارشنبه",
        "visits": 3892
      },
      {
        "day": "پنج‌شنبه",
        "visits": 3891
      },
      {
        "day": "جمعه",
        "visits": 3893
      }
    ]
  }
]