[
  {
    "title": "تعداد بازدید وب‌سایت‌ها",
    "value": 1099490,
    "growth": 10,
    "chartData": [
      {
        "day": "شنبه",
        "visits": 154212
      },
      {
        "day": "یک‌شنبه",
        "visits": 167062
      },
      {
        "day": "دوشنبه",
        "visits": 149342
      },
      {
        "day": "سه‌شنبه",
        "visits": 157452
      },
      {
        "day": "چهارشنبه",
        "visits": 164812
      },
      {
        "day": "پنج‌شنبه",
        "visits": 178142
      },
      {
        "day": "جمعه",
        "visits": 146372
      }
    ]
  },
  {
    "title": "تعداد کاربران جدید",
    "value": 4383,
    "growth": 5,
    "chartData": [
      {
        "day": "شنبه",
        "visits": 5160
      },
      {
        "day": "یک‌شنبه",
        "visits": 5167
      },
      {
        "day": "دوشنبه",
        "visits": 5162
      },
      {
        "day": "سه‌شنبه",
        "visits": 5171
      },
      {
        "day": "چهارشنبه",
        "visits": 5164
      },
      {
        "day": "پنج‌شنبه",
        "visits": 5166
      },
      {
        "day": "جمعه",
        "visits": 5177
      }
    ]
  },
  {
    "title": "وب‌سایت‌های زیرمجموعه",
    "value": 4345,
    "growth": 3,
    "chartData": [
      {
        "day": "شنبه",
        "visits": 5170
      },
      {
        "day": "یک‌شنبه",
        "visits": 5167
      },
      {
        "day": "دوشنبه",
        "visits": 5195
      },
      {
        "day": "سه‌شنبه",
        "visits": 5169
      },
      {
        "day": "چهارشنبه",
        "visits": 5163
      },
      {
        "day": "پنج‌شنبه",
        "visits": 5196
      },
      {
        "day": "جمعه",
        "visits": 5169
      }
    ]
  },
  {
    "title": "سرورهای فعال",
    "value": 4383,
    "growth": 2,
    "chartData": [
      {
        "day": "شنبه",
        "visits": 5162
      },
      {
        "day": "یک‌شنبه",
        "visits": 5163
      },
      {
        "day": "دوشنبه",
        "visits": 5169
      },
      {
        "day": "سه‌شنبه",
        "visits": 5171
      },
      {
        "day": "چهارشنبه",
        "visits": 5167
      },
      {
        "day": "پنج‌شنبه",
        "visits": 5164
      },
      {
        "day": "جمعه",
        "visits": 5251
      }
    ]
  },
  {
    "title": "تحلیل‌های امروز",
    "value": 4417,
    "growth": 4,
    "chartData": [
      {
        "day": "شنبه",
        "visits": 5247
      },
      {
        "day": "یک‌شنبه",
        "visits": 5158
      },
      {
        "day": "دوشنبه",
        "visits": 5249
      },
      {
        "day": "سه‌شنبه",
        "visits": 5159
      },
      {
        "day": "چهارشنبه",
        "visits": 5160
      },
      {
        "day": "پنج‌شنبه",
        "visits": 5349
      },
      {
        "day": "جمعه",
        "visits": 5349
      }
    ]
  },
  {
    "title": "قطع همکاری‌های هفته اخیر",
    "value": 4391,
    "growth": -9,
    "chartData": [
      {
        "day": "شنبه",
        "visits": 5199
      },
      {
        "day": "یک‌شنبه",
        "visits": 5192
      },
      {
        "day": "دوشنبه",
        "visits": 5201
      },
      {
        "day": "سه‌شنبه",
        "visits": 5193
      },
      {
        "day": "چهارشنبه",
        "visits": 5200
      },
      {
        "day": "پنج‌شنبه",
        "visits": 5199
      },
      {
        "day": "جمعه",
        "visits": 5201
      }
    ]
  }
]