[
  {
    "title": "تعداد بازدید وب‌سایت‌ها",
    "value": 1150810,
    "growth": 10,
    "chartData": [
      {
        "day": "شنبه",
        "visits": 215796
      },
      {
        "day": "یک‌شنبه",
        "visits": 228646
      },
      {
        "day": "دوشنبه",
        "visits": 210926
      },
      {
        "day": "سه‌شنبه",
        "visits": 219036
      },
      {
        "day": "چهارشنبه",
        "visits": 226396
      },
      {
        "day": "پنج‌شنبه",
        "visits": 239726
      },
      {
        "day": "جمعه",
        "visits": 207956
      }
    ]
  },
  {
    "title": "تعداد کاربران جدید",
    "value": 51603,
    "growth": 5,
    "chartData": [
      {
        "day": "شنبه",
        "visits": 61944
      },
      {
        "day": "یک‌شنبه",
        "visits": 61951
      },
      {
        "day": "دوشنبه",
        "visits": 61946
      },
      {
        "day": "سه‌شنبه",
        "visits": 61955
      },
      {
        "day": "چهارشنبه",
        "visits": 61948
      },
      {
        "day": "پنج‌شنبه",
        "visits": 61950
      },
      {
        "day": "جمعه",
        "visits": 61961
      }
    ]
  },
  {
    "title": "وب‌سایت‌های زیرمجموعه",
    "value": 55665,
    "growth": 3,
    "chartData": [
      {
        "day": "شنبه",
        "visits": 61954
      },
      {
        "day": "یک‌شنبه",
        "visits": 61951
      },
      {
        "day": "دوشنبه",
        "visits": 61879
      },
      {
        "day": "سه‌شنبه",
        "visits": 61953
      },
      {
        "day": "چهارشنبه",
        "visits": 61947
      },
      {
        "day": "پنج‌شنبه",
        "visits": 61880
      },
      {
        "day": "جمعه",
        "visits": 61953
      }
    ]
  },
  {
    "title": "سرورهای فعال",
    "value": 51603,
    "growth": 2,
    "chartData": [
      {
        "day": "شنبه",
        "visits": 61946
      },
      {
        "day": "یک‌شنبه",
        "visits": 61947
      },
      {
        "day": "دوشنبه",
        "visits": 61953
      },
      {
        "day": "سه‌شنبه",
        "visits": 61955
      },
      {
        "day": "چهارشنبه",
        "visits": 61951
      },
      {
        "day": "پنج‌شنبه",
        "visits": 61948
      },
      {
        "day": "جمعه",
        "visits": 61935
      }
    ]
  },
  {
    "title": "تحلیل‌های امروز",
    "value": 51637,
    "growth": 4,
    "chartData": [
      {
        "day": "شنبه",
        "visits": 61931
      },
      {
        "day": "یک‌شنبه",
        "visits": 61942
      },
      {
        "day": "دوشنبه",
        "visits": 61933
      },
      {
        "day": "سه‌شنبه",
        "visits": 61943
      },
      {
        "day": "چهارشنبه",
        "visits": 61944
      },
      {
        "day": "پنج‌شنبه",
        "visits": 61933
      },
      {
        "day": "جمعه",
        "visits": 61933
      }
    ]
  },
  {
    "title": "قطع همکاری‌های هفته اخیر",
    "value": 51611,
    "growth": -9,
    "chartData": [
      {
        "day": "شنبه",
        "visits": 61883
      },
      {
        "day": "یک‌شنبه",
        "visits": 61876
      },
      {
        "day": "دوشنبه",
        "visits": 61885
      },
      {
        "day": "سه‌شنبه",
        "visits": 61877
      },
      {
        "day": "چهارشنبه",
        "visits": 61784
      },
      {
        "day": "پنج‌شنبه",
        "visits": 61783
      },
      {
        "day": "جمعه",
        "visits": 61785
      }
    ]
  }
]