[
  {
    "title": "تعداد بازدید وب‌سایت‌ها",
    "value": 1119310,
    "growth": 10,
    "chartData": [
      {
        "day": "شنبه",
        "visits": 177996
      },
      {
        "day": "یک‌شنبه",
        "visits": 190846
      },
      {
        "day": "دوشنبه",
        "visits": 173126
      },
      {
        "day": "سه‌شنبه",
        "visits": 181236
      },
      {
        "day": "چهارشنبه",
        "visits": 188596
      },
      {
        "day": "پنج‌شنبه",
        "visits": 201926
      },
      {
        "day": "جمعه",
        "visits": 170156
      }
    ]
  },
  {
    "title": "تعداد کاربران جدید",
    "value": 20103,
    "growth": 5,
    "chartData": [
      {
        "day": "شنبه",
        "visits": 24144
      },
      {
        "day": "یک‌شنبه",
        "visits": 24151
      },
      {
        "day": "دوشنبه",
        "visits": 24146
      },
      {
        "day": "سه‌شنبه",
        "visits": 24155
      },
      {
        "day": "چهارشنبه",
        "visits": 24148
      },
      {
        "day": "پنج‌شنبه",
        "visits": 24150
      },
      {
        "day": "جمعه",
        "visits": 24161
      }
    ]
  },
  {
    "title": "وب‌سایت‌های زیرمجموعه",
    "value": 24165,
    "growth": 3,
    "chartData": [
      {
        "day": "شنبه",
        "visits": 24154
      },
      {
        "day": "یک‌شنبه",
        "visits": 24151
      },
      {
        "day": "دوشنبه",
        "visits": 24079
      },
      {
        "day": "سه‌شنبه",
        "visits": 24153
      },
      {
        "day": "چهارشنبه",
        "visits": 24147
      },
      {
        "day": "پنج‌شنبه",
        "visits": 24080
      },
      {
        "day": "جمعه",
        "visits": 24153
      }
    ]
  },
  {
    "title": "سرورهای فعال",
    "value": 20103,
    "growth": 2,
    "chartData": [
      {
        "day": "شنبه",
        "visits": 24146
      },
      {
        "day": "یک‌شنبه",
        "visits": 24147
      },
      {
        "day": "دوشنبه",
        "visits": 24153
      },
      {
        "day": "سه‌شنبه",
        "visits": 24155
      },
      {
        "day": "چهارشنبه",
        "visits": 24151
      },
      {
        "day": "پنج‌شنبه",
        "visits": 24148
      },
      {
        "day": "جمعه",
        "visits": 24135
      }
    ]
  },
  {
    "title": "تحلیل‌های امروز",
    "value": 20137,
    "growth": 4,
    "chartData": [
      {
        "day": "شنبه",
        "visits": 24131
      },
      {
        "day": "یک‌شنبه",
        "visits": 24142
      },
      {
        "day": "دوشنبه",
        "visits": 24133
      },
      {
        "day": "سه‌شنبه",
        "visits": 24143
      },
      {
        "day": "چهارشنبه",
        "visits": 24144
      },
      {
        "day": "پنج‌شنبه",
        "visits": 24133
      },
      {
        "day": "جمعه",
        "visits": 24133
      }
    ]
  },
  {
    "title": "قطع همکاری‌های هفته اخیر",
    "value": 20111,
    "growth": -9,
    "chartData": [
      {
        "day": "شنبه",
        "visits": 24083
      },
      {
        "day": "یک‌شنبه",
        "visits": 24076
      },
      {
        "day": "دوشنبه",
        "visits": 24085
      },
      {
        "day": "سه‌شنبه",
        "visits": 24077
      },
      {
        "day": "چهارشنبه",
        "visits": 23984
      },
      {
        "day": "پنج‌شنبه",
        "visits": 23983
      },
      {
        "day": "جمعه",
        "visits": 23985
      }
    ]
  }
]