[
  {
    "title": "تعداد بازدید وب‌سایت‌ها",
    "value": 1104390,
    "growth": 10,
    "chartData": [
      {
        "day": "شنبه",
        "visits": 160092
      },
      {
        "day": "یک‌شنبه",
        "visits": 172942
      },
      {
        "day": "دوشنبه",
        "visits": 155222
      },
      {
        "day": "سه‌شنبه",
        "visits": 163332
      },
      {
        "day": "چهارشنبه",
        "visits": 170692
      },
      {
        "day": "پنج‌شنبه",
        "visits": 184022
      },
      {
        "day": "جمعه",
        "visits": 152252
      }
    ]
  },
  {
    "title": "تعداد کاربران جدید",
    "value": 5183,
    "growth": 5,
    "chartData": [
      {
        "day": "شنبه",
        "visits": 6240
      },
      {
        "day": "یک‌شنبه",
        "visits": 6247
      },
      {
        "day": "دوشنبه",
        "visits": 6242
      },
      {
        "day": "سه‌شنبه",
        "visits": 6251
      },
      {
        "day": "چهارشنبه",
        "visits": 6244
      },
      {
        "day": "پنج‌شنبه",
        "visits": 6246
      },
      {
        "day": "جمعه",
        "visits": 6257
      }
    ]
  },
  {
    "title": "وب‌سایت‌های زیرمجموعه",
    "value": 9245,
    "growth": 3,
    "chartData": [
      {
        "day": "شنبه",
        "visits": 6250
      },
      {
        "day": "یک‌شنبه",
        "visits": 6247
      },
      {
        "day": "دوشنبه",
        "visits": 6175
      },
      {
        "day": "سه‌شنبه",
        "visits": 6249
      },
      {
        "day": "چهارشنبه",
        "visits": 6243
      },
      {
        "day": "پنج‌شنبه",
        "visits": 6176
      },
      {
        "day": "جمعه",
        "visits": 6249
      }
    ]
  },
  {
    "title": "سرورهای فعال",
    "value": 5183,
    "growth": 2,
    "chartData": [
      {
        "day": "شنبه",
        "visits": 6242
      },
      {
        "day": "یک‌شنبه",
        "visits": 6243
      },
      {
        "day": "دوشنبه",
        "visits": 6249
      },
      {
        "day": "سه‌شنبه",
        "visits": 6251
      },
      {
        "day": "چهارشنبه",
        "visits": 6247
      },
      {
        "day": "پنج‌شنبه",
        "visits": 6244
      },
      {
        "day": "جمعه",
        "visits": 6231
      }
    ]
  },
  {
    "title": "تحلیل‌های امروز",
    "value": 5217,
    "growth": 4,
    "chartData": [
      {
        "day": "شنبه",
        "visits": 6227
      },
      {
        "day": "یک‌شنبه",
        "visits": 6238
      },
      {
        "day": "دوشنبه",
        "visits": 6229
      },
      {
        "day": "سه‌شنبه",
        "visits": 6239
      },
      {
        "day": "چهارشنبه",
        "visits": 6240
      },
      {
        "day": "پنج‌شنبه",
        "visits": 6229
      },
      {
        "day": "جمعه",
        "visits": 6229
      }
    ]
  },
  {
    "title": "قطع همکاری‌های هفته اخیر",
    "value": 5191,
    "growth": -9,
    "chartData": [
      {
        "day": "شنبه",
        "visits": 6179
      },
      {
        "day": "یک‌شنبه",
        "visits": 6172
      },
      {
        "day": "دوشنبه",
        "visits": 6181
      },
      {
        "day": "سه‌شنبه",
        "visits": 6173
      },
      {
        "day": "چهارشنبه",
        "visits": 6080
      },
      {
        "day": "پنج‌شنبه",
        "visits": 6079
      },
      {
        "day": "جمعه",
        "visits": 6081
      }
    ]
  }
]