[
  {
    "title": "تعداد بازدید وب‌سایت‌ها",
    "value": 1132250,
    "growth": 10,
    "chartData": [
      {
        "day": "شنبه",
        "visits": 193524
      },
      {
        "day": "یک‌شنبه",
        "visits": 206374
      },
      {
        "day": "دوشنبه",
        "visits": 188654
      },
      {
        "day": "سه‌شنبه",
        "visits": 196764
      },
      {
        "day": "چهارشنبه",
        "visits": 204124
      },
      {
        "day": "پنج‌شنبه",
        "visits": 217454
      },
      {
        "day": "جمعه",
        "visits": 185684
      }
    ]
  },
  {
    "title": "تعداد کاربران جدید",
    "value": 33043,
    "growth": 5,
    "chartData": [
      {
        "day": "شنبه",
        "visits": 39672
      },
      {
        "day": "یک‌شنبه",
        "visits": 39679
      },
      {
        "day": "دوشنبه",
        "visits": 39674
      },
      {
        "day": "سه‌شنبه",
        "visits": 39683
      },
      {
        "day": "چهارشنبه",
        "visits": 39676
      },
      {
        "day": "پنج‌شنبه",
        "visits": 39678
      },
      {
        "day": "جمعه",
        "visits": 39689
      }
    ]
  },
  {
    "title": "وب‌سایت‌های زیرمجموعه",
    "value": 37105,
    "growth": 3,
    "chartData": [
      {
        "day": "شنبه",
        "visits": 39682
      },
      {
        "day": "یک‌شنبه",
        "visits": 39679
      },
      {
        "day": "دوشنبه",
        "visits": 39607
      },
      {
        "day": "سه‌شنبه",
        "visits": 39681
      },
      {
        "day": "چهارشنبه",
        "visits": 39675
      },
      {
        "day": "پنج‌شنبه",
        "visits": 39608
      },
      {
        "day": "جمعه",
        "visits": 39681
      }
    ]
  },
  {
    "title": "سرورهای فعال",
    "value": 33043,
    "growth": 2,
    "chartData": [
      {
        "day": "شنبه",
        "visits": 39674
      },
      {
        "day": "یک‌شنبه",
        "visits": 39675
      },
      {
        "day": "دوشنبه",
        "visits": 39681
      },
      {
        "day": "سه‌شنبه",
        "visits": 39683
      },
      {
        "day": "چهارشنبه",
        "visits": 39679
      },
      {
        "day": "پنج‌شنبه",
        "visits": 39676
      },
      {
        "day": "جمعه",
        "visits": 39663
      }
    ]
  },
  {
    "title": "تحلیل‌های امروز",
    "value": 33077,
    "growth": 4,
    "chartData": [
      {
        "day": "شنبه",
        "visits": 39659
      },
      {
        "day": "یک‌شنبه",
        "visits": 39670
      },
      {
        "day": "دوشنبه",
        "visits": 39661
      },
      {
        "day": "سه‌شنبه",
        "visits": 39671
      },
      {
        "day": "چهارشنبه",
        "visits": 39672
      },
      {
        "day": "پنج‌شنبه",
        "visits": 39661
      },
      {
        "day": "جمعه",
        "visits": 39661
      }
    ]
  },
  {
    "title": "قطع همکاری‌های هفته اخیر",
    "value": 33051,
    "growth": -9,
    "chartData": [
      {
        "day": "شنبه",
        "visits": 39611
      },
      {
        "day": "یک‌شنبه",
        "visits": 39604
      },
      {
        "day": "دوشنبه",
        "visits": 39613
      },
      {
        "day": "سه‌شنبه",
        "visits": 39605
      },
      {
        "day": "چهارشنبه",
        "visits": 39512
      },
      {
        "day": "پنج‌شنبه",
        "visits": 39511
      },
      {
        "day": "جمعه",
        "visits": 39513
      }
    ]
  }
]