[
  {
    "title": "تعداد بازدید وب‌سایت‌ها",
    "value": 1106870,
    "growth": 10,
    "chartData": [
      {
        "day": "شنبه",
        "visits": 163068
      },
      {
        "day": "یک‌شنبه",
        "visits": 175918
      },
      {
        "day": "دوشنبه",
        "visits": 158198
      },
      {
        "day": "سه‌شنبه",
        "visits": 166308
      },
      {
        "day": "چهارشنبه",
        "visits": 173668
      },
      {
        "day": "پنج‌شنبه",
        "visits": 186998
      },
      {
        "day": "جمعه",
        "visits": 155228
      }
    ]
  },
  {
    "title": "تعداد کاربران جدید",
    "value": 7663,
    "growth": 5,
    "chartData": [
      {
        "day": "شنبه",
        "visits": 9216
      },
      {
        "day": "یک‌شنبه",
        "visits": 9223
      },
      {
        "day": "دوشنبه",
        "visits": 9218
      },
      {
        "day": "سه‌شنبه",
        "visits": 9227
      },
      {
        "day": "چهارشنبه",
        "visits": 9220
      },
      {
        "day": "پنج‌شنبه",
        "visits": 9222
      },
      {
        "day": "جمعه",
        "visits": 9233
      }
    ]
  },
  {
    "title": "وب‌سایت‌های زیرمجموعه",
    "value": 11725,
    "growth": 3,
    "chartData": [
      {
        "day": "شنبه",
        "visits": 9226
      },
      {
        "day": "یک‌شنبه",
        "visits": 9223
      },
      {
        "day": "دوشنبه",
        "visits": 9151
      },
      {
        "day": "سه‌شنبه",
        "visits": 9225
      },
      {
        "day": "چهارشنبه",
        "visits": 9219
      },
      {
        "day": "پنج‌شنبه",
        "visits": 9152
      },
      {
        "day": "جمعه",
        "visits": 9225
      }
    ]
  },
  {
    "title": "سرورهای فعال",
    "value": 7663,
    "growth": 2,
    "chartData": [
      {
        "day": "شنبه",
        "visits": 9218
      },
      {
        "day": "یک‌شنبه",
        "visits": 9219
      },
      {
        "day": "دوشنبه",
        "visits": 9225
      },
      {
        "day": "سه‌شنبه",
        "visits": 9227
      },
      {
        "day": "چهارشنبه",
        "visits": 9223
      },
      {
        "day": "پنج‌شنبه",
        "visits": 9220
      },
      {
        "day": "جمعه",
        "visits": 9207
      }
    ]
  },
  {
    "title": "تحلیل‌های امروز",
    "value": 7697,
    "growth": 4,
    "chartData": [
      {
        "day": "شنبه",
        "visits": 9203
      },
      {
        "day": "یک‌شنبه",
        "visits": 9214
      },
      {
        "day": "دوشنبه",
        "visits": 9205
      },
      {
        "day": "سه‌شنبه",
        "visits": 9215
      },
      {
        "day": "چهارشنبه",
        "visits": 9216
      },
      {
        "day": "پنج‌شنبه",
        "visits": 9205
      },
      {
        "day": "جمعه",
        "visits": 9205
      }
    ]
  },
  {
    "title": "قطع همکاری‌های هفته اخیر",
    "value": 7671,
    "growth": -9,
    "chartData": [
      {
        "day": "شنبه",
        "visits": 9155
      },
      {
        "day": "یک‌شنبه",
        "visits": 9148
      },
      {
        "day": "دوشنبه",
        "visits": 9157
      },
      {
        "day": "سه‌شنبه",
        "visits": 9149
      },
      {
        "day": "چهارشنبه",
        "visits": 9056
      },
      {
        "day": "پنج‌شنبه",
        "visits": 9055
      },
      {
        "day": "جمعه",
        "visits": 9057
      }
    ]
  }
]