[
  {
    "title": "تعداد بازدید وب‌سایت‌ها",
    "value": 1118710,
    "growth": 10,
    "chartData": [
      {
        "day": "شنبه",
        "visits": 177276
      },
      {
        "day": "یک‌شنبه",
        "visits": 190126
      },
      {
        "day": "دوشنبه",
        "visits": 172406
      },
      {
        "day": "سه‌شنبه",
        "visits": 180516
      },
      {
        "day": "چهارشنبه",
        "visits": 187876
      },
      {
        "day": "پنج‌شنبه",
        "visits": 201206
      },
      {
        "day": "جمعه",
        "visits": 169436
      }
    ]
  },
  {
    "title": "تعداد کاربران جدید",
    "value": 19503,
    "growth": 5,
    "chartData": [
      {
        "day": "شنبه",
        "visits": 23424
      },
      {
        "day": "یک‌شنبه",
        "visits": 23431
      },
      {
        "day": "دوشنبه",
        "visits": 23426
      },
      {
        "day": "سه‌شنبه",
        "visits": 23435
      },
      {
        "day": "چهارشنبه",
        "visits": 23428
      },
      {
        "day": "پنج‌شنبه",
        "visits": 23430
      },
      {
        "day": "جمعه",
        "visits": 23441
      }
    ]
  },
  {
    "title": "وب‌سایت‌های زیرمجموعه",
    "value": 23565,
    "growth": 3,
    "chartData": [
      {
        "day": "شنبه",
        "visits": 23434
      },
      {
        "day": "یک‌شنبه",
        "visits": 23431
      },
      {
        "day": "دوشنبه",
        "visits": 23359
      },
      {
        "day": "سه‌شنبه",
        "visits": 23433
      },
      {
        "day": "چهارشنبه",
        "visits": 23427
      },
      {
        "day": "پنج‌شنبه",
        "visits": 23360
      },
      {
        "day": "جمعه",
        "visits": 23433
      }
    ]
  },
  {
    "title": "سرورهای فعال",
    "value": 19503,
    "growth": 2,
    "chartData": [
      {
        "day": "شنبه",
        "visits": 23426
      },
      {
        "day": "یک‌شنبه",
        "visits": 23427
      },
      {
        "day": "دوشنبه",
        "visits": 23433
      },
      {
        "day": "سه‌شنبه",
        "visits": 23435
      },
      {
        "day": "چهارشنبه",
        "visits": 23431
      },
      {
        "day": "پنج‌شنبه",
        "visits": 23428
      },
      {
        "day": "جمعه",
        "visits": 23415
      }
    ]
  },
  {
    "title": "تحلیل‌های امروز",
    "value": 19537,
    "growth": 4,
    "chartData": [
      {
        "day": "شنبه",
        "visits": 23411
      },
      {
        "day": "یک‌شنبه",
        "visits": 23422
      },
      {
        "day": "دوشنبه",
        "visits": 23413
      },
      {
        "day": "سه‌شنبه",
        "visits": 23423
      },
      {
        "day": "چهارشنبه",
        "visits": 23424
      },
      {
        "day": "پنج‌شنبه",
        "visits": 23413
      },
      {
        "day": "جمعه",
        "visits": 23413
      }
    ]
  },
  {
    "title": "قطع همکاری‌های هفته اخیر",
    "value": 19511,
    "growth": -9,
    "chartData": [
      {
        "day": "شنبه",
        "visits": 23363
      },
      {
        "day": "یک‌شنبه",
        "visits": 23356
      },
      {
        "day": "دوشنبه",
        "visits": 23365
      },
      {
        "day": "سه‌شنبه",
        "visits": 23357
      },
      {
        "day": "چهارشنبه",
        "visits": 23264
      },
      {
        "day": "پنج‌شنبه",
        "visits": 23263
      },
      {
        "day": "جمعه",
        "visits": 23265
      }
    ]
  }
]