[
  {
    "title": "تعداد بازدید وب‌سایت‌ها",
    "value": 1104060,
    "growth": 10,
    "chartData": [
      {
        "day": "شنبه",
        "visits": 159696
      },
      {
        "day": "یک‌شنبه",
        "visits": 172546
      },
      {
        "day": "دوشنبه",
        "visits": 154826
      },
      {
        "day": "سه‌شنبه",
        "visits": 162936
      },
      {
        "day": "چهارشنبه",
        "visits": 170296
      },
      {
        "day": "پنج‌شنبه",
        "visits": 183626
      },
      {
        "day": "جمعه",
        "visits": 151856
      }
    ]
  },
  {
    "title": "تعداد کاربران جدید",
    "value": 4853,
    "growth": 5,
    "chartData": [
      {
        "day": "شنبه",
        "visits": 5844
      },
      {
        "day": "یک‌شنبه",
        "visits": 5851
      },
      {
        "day": "دوشنبه",
        "visits": 5846
      },
      {
        "day": "سه‌شنبه",
        "visits": 5855
      },
      {
        "day": "چهارشنبه",
        "visits": 5848
      },
      {
        "day": "پنج‌شنبه",
        "visits": 5850
      },
      {
        "day": "جمعه",
        "visits": 5861
      }
    ]
  },
  {
    "title": "وب‌سایت‌های زیرمجموعه",
    "value": 8915,
    "growth": 3,
    "chartData": [
      {
        "day": "شنبه",
        "visits": 5854
      },
      {
        "day": "یک‌شنبه",
        "visits": 5851
      },
      {
        "day": "دوشنبه",
        "visits": 5779
      },
      {
        "day": "سه‌شنبه",
        "visits": 5853
      },
      {
        "day": "چهارشنبه",
        "visits": 5847
      },
      {
        "day": "پنج‌شنبه",
        "visits": 5780
      },
      {
        "day": "جمعه",
        "visits": 5853
      }
    ]
  },
  {
    "title": "سرورهای فعال",
    "value": 4853,
    "growth": 2,
    "chartData": [
      {
        "day": "شنبه",
        "visits": 5846
      },
      {
        "day": "یک‌شنبه",
        "visits": 5847
      },
      {
        "day": "دوشنبه",
        "visits": 5853
      },
      {
        "day": "سه‌شنبه",
        "visits": 5855
      },
      {
        "day": "چهارشنبه",
        "visits": 5851
      },
      {
        "day": "پنج‌شنبه",
        "visits": 5848
      },
      {
        "day": "جمعه",
        "visits": 5835
      }
    ]
  },
  {
    "title": "تحلیل‌های امروز",
    "value": 4887,
    "growth": 4,
    "chartData": [
      {
        "day": "شنبه",
        "visits": 5831
      },
      {
        "day": "یک‌شنبه",
        "visits": 5842
      },
      {
        "day": "دوشنبه",
        "visits": 5833
      },
      {
        "day": "سه‌شنبه",
        "visits": 5843
      },
      {
        "day": "چهارشنبه",
        "visits": 5844
      },
      {
        "day": "پنج‌شنبه",
        "visits": 5833
      },
      {
        "day": "جمعه",
        "visits": 5833
      }
    ]
  },
  {
    "title": "قطع همکاری‌های هفته اخیر",
    "value": 4861,
    "growth": -9,
    "chartData": [
      {
        "day": "شنبه",
        "visits": 5783
      },
      {
        "day": "یک‌شنبه",
        "visits": 5776
      },
      {
        "day": "دوشنبه",
        "visits": 5785
      },
      {
        "day": "سه‌شنبه",
        "visits": 5777
      },
      {
        "day": "چهارشنبه",
        "visits": 5684
      },
      {
        "day": "پنج‌شنبه",
        "visits": 5683
      },
      {
        "day": "جمعه",
        "visits": 5685
      }
    ]
  }
]