[
  {
    "title": "تعداد بازدید وب‌سایت‌ها",
    "value": 1150460,
    "growth": 10,
    "chartData": [
      {
        "day": "شنبه",
        "visits": 215376
      },
      {
        "day": "یک‌شنبه",
        "visits": 228226
      },
      {
        "day": "دوشنبه",
        "visits": 210506
      },
      {
        "day": "سه‌شنبه",
        "visits": 218616
      },
      {
        "day": "چهارشنبه",
        "visits": 225976
      },
      {
        "day": "پنج‌شنبه",
        "visits": 239306
      },
      {
        "day": "جمعه",
        "visits": 207536
      }
    ]
  },
  {
    "title": "تعداد کاربران جدید",
    "value": 51253,
    "growth": 5,
    "chartData": [
      {
        "day": "شنبه",
        "visits": 61524
      },
      {
        "day": "یک‌شنبه",
        "visits": 61531
      },
      {
        "day": "دوشنبه",
        "visits": 61526
      },
      {
        "day": "سه‌شنبه",
        "visits": 61535
      },
      {
        "day": "چهارشنبه",
        "visits": 61528
      },
      {
        "day": "پنج‌شنبه",
        "visits": 61530
      },
      {
        "day": "جمعه",
        "visits": 61541
      }
    ]
  },
  {
    "title": "وب‌سایت‌های زیرمجموعه",
    "value": 55315,
    "growth": 3,
    "chartData": [
      {
        "day": "شنبه",
        "visits": 61534
      },
      {
        "day": "یک‌شنبه",
        "visits": 61531
      },
      {
        "day": "دوشنبه",
        "visits": 61459
      },
      {
        "day": "سه‌شنبه",
        "visits": 61533
      },
      {
        "day": "چهارشنبه",
        "visits": 61527
      },
      {
        "day": "پنج‌شنبه",
        "visits": 61460
      },
      {
        "day": "جمعه",
        "visits": 61533
      }
    ]
  },
  {
    "title": "سرورهای فعال",
    "value": 51253,
    "growth": 2,
    "chartData": [
      {
        "day": "شنبه",
        "visits": 61526
      },
      {
        "day": "یک‌شنبه",
        "visits": 61527
      },
      {
        "day": "دوشنبه",
        "visits": 61533
      },
      {
        "day": "سه‌شنبه",
        "visits": 61535
      },
      {
        "day": "چهارشنبه",
        "visits": 61531
      },
      {
        "day": "پنج‌شنبه",
        "visits": 61528
      },
      {
        "day": "جمعه",
        "visits": 61515
      }
    ]
  },
  {
    "title": "تحلیل‌های امروز",
    "value": 51287,
    "growth": 4,
    "chartData": [
      {
        "day": "شنبه",
        "visits": 61511
      },
      {
        "day": "یک‌شنبه",
        "visits": 61522
      },
      {
        "day": "دوشنبه",
        "visits": 61513
      },
      {
        "day": "سه‌شنبه",
        "visits": 61523
      },
      {
        "day": "چهارشنبه",
        "visits": 61524
      },
      {
        "day": "پنج‌شنبه",
        "visits": 61513
      },
      {
        "day": "جمعه",
        "visits": 61513
      }
    ]
  },
  {
    "title": "قطع همکاری‌های هفته اخیر",
    "value": 51261,
    "growth": -9,
    "chartData": [
      {
        "day": "شنبه",
        "visits": 61463
      },
      {
        "day": "یک‌شنبه",
        "visits": 61456
      },
      {
        "day": "دوشنبه",
        "visits": 61465
      },
      {
        "day": "سه‌شنبه",
        "visits": 61457
      },
      {
        "day": "چهارشنبه",
        "visits": 61364
      },
      {
        "day": "پنج‌شنبه",
        "visits": 61363
      },
      {
        "day": "جمعه",
        "visits": 61365
      }
    ]
  }
]