[
  {
    "title": "تعداد بازدید وب‌سایت‌ها",
    "value": 1131350,
    "growth": 10,
    "chartData": [
      {
        "day": "شنبه",
        "visits": 192444
      },
      {
        "day": "یک‌شنبه",
        "visits": 205294
      },
      {
        "day": "دوشنبه",
        "visits": 187574
      },
      {
        "day": "سه‌شنبه",
        "visits": 195684
      },
      {
        "day": "چهارشنبه",
        "visits": 203044
      },
      {
        "day": "پنج‌شنبه",
        "visits": 216374
      },
      {
        "day": "جمعه",
        "visits": 184604
      }
    ]
  },
  {
    "title": "تعداد کاربران جدید",
    "value": 32143,
    "growth": 5,
    "chartData": [
      {
        "day": "شنبه",
        "visits": 38592
      },
      {
        "day": "یک‌شنبه",
        "visits": 38599
      },
      {
        "day": "دوشنبه",
        "visits": 38594
      },
      {
        "day": "سه‌شنبه",
        "visits": 38603
      },
      {
        "day": "چهارشنبه",
        "visits": 38596
      },
      {
        "day": "پنج‌شنبه",
        "visits": 38598
      },
      {
        "day": "جمعه",
        "visits": 38609
      }
    ]
  },
  {
    "title": "وب‌سایت‌های زیرمجموعه",
    "value": 36205,
    "growth": 3,
    "chartData": [
      {
        "day": "شنبه",
        "visits": 38602
      },
      {
        "day": "یک‌شنبه",
        "visits": 38599
      },
      {
        "day": "دوشنبه",
        "visits": 38527
      },
      {
        "day": "سه‌شنبه",
        "visits": 38601
      },
      {
        "day": "چهارشنبه",
        "visits": 38595
      },
      {
        "day": "پنج‌شنبه",
        "visits": 38528
      },
      {
        "day": "جمعه",
        "visits": 38601
      }
    ]
  },
  {
    "title": "سرورهای فعال",
    "value": 32143,
    "growth": 2,
    "chartData": [
      {
        "day": "شنبه",
        "visits": 38594
      },
      {
        "day": "یک‌شنبه",
        "visits": 38595
      },
      {
        "day": "دوشنبه",
        "visits": 38601
      },
      {
        "day": "سه‌شنبه",
        "visits": 38603
      },
      {
        "day": "چهارشنبه",
        "visits": 38599
      },
      {
        "day": "پنج‌شنبه",
        "visits": 38596
      },
      {
        "day": "جمعه",
        "visits": 38583
      }
    ]
  },
  {
    "title": "تحلیل‌های امروز",
    "value": 32177,
    "growth": 4,
    "chartData": [
      {
        "day": "شنبه",
        "visits": 38579
      },
      {
        "day": "یک‌شنبه",
        "visits": 38590
      },
      {
        "day": "دوشنبه",
        "visits": 38581
      },
      {
        "day": "سه‌شنبه",
        "visits": 38591
      },
      {
        "day": "چهارشنبه",
        "visits": 38592
      },
      {
        "day": "پنج‌شنبه",
        "visits": 38581
      },
      {
        "day": "جمعه",
        "visits": 38581
      }
    ]
  },
  {
    "title": "قطع همکاری‌های هفته اخیر",
    "value": 32151,
    "growth": -9,
    "chartData": [
      {
        "day": "شنبه",
        "visits": 38531
      },
      {
        "day": "یک‌شنبه",
        "visits": 38524
      },
      {
        "day": "دوشنبه",
        "visits": 38533
      },
      {
        "day": "سه‌شنبه",
        "visits": 38525
      },
      {
        "day": "چهارشنبه",
        "visits": 38432
      },
      {
        "day": "پنج‌شنبه",
        "visits": 38431
      },
      {
        "day": "جمعه",
        "visits": 38433
      }
    ]
  }
]